{"Empleados":[{"direccion":"Calle Romeria Nº10, Barrio Jarana, 11518","telefono":574890398,"nombre":"admin","email":"admin"},{"direccion":"Barrio Jarana 11518","telefono":738492039,"nombre":"Pedro Garcia","email":"pedroG@gmail.com"},{"direccion":"Cadiz 11001","telefono":639488567,"nombre":"Jorge Martinez","email":"jorgerM@gmail.com"},{"direccion":"Puerto Real 11510","telefono":784938173,"nombre":"Luis Garcia","email":"luisG@gmail.com"},{"direccion":"Puerto Real 11510","telefono":674838983,"nombre":"Manuel Romero","email":"manuelR@gmail.com"}],"Vehiculos":[{"fecha_revision":"2020-04-30","fecha_compra":"2020-04-13","matricula":"7583-KLM","documentacion":"prueba.txt"},{"fecha_revision":"2020-04-30","fecha_compra":"2020-04-27","matricula":"0134-LDP","documentacion":"prueba.txt"},{"fecha_revision":"2020-06-18","fecha_compra":"2020-04-13","matricula":"8792-LCD","documentacion":"prueba.txt"},{"fecha_revision":"2020-04-30","fecha_compra":"2020-02-12","matricula":"1934-HDX","documentacion":"prueba.txt"},{"fecha_revision":"2021-09-24","fecha_compra":"2020-04-01","matricula":"8459-CCC","documentacion":"Protocolo.pdf"},{"fecha_revision":"2020-04-23","fecha_compra":"2020-04-01","matricula":"8492-DCP","documentacion":"Protocolo.pdf"},{"fecha_revision":"2020-04-29","fecha_compra":"2020-04-16","matricula":"8948-LBB","documentacion":"Protocolo.pdf"},{"fecha_revision":"2020-10-28","fecha_compra":"2020-04-17","matricula":"7712-DFG","documentacion":"prueba.txt"},{"fecha_revision":"2020-04-30","fecha_compra":"2020-04-05","matricula":"8593-JDK","documentacion":"prueba.txt"},{"fecha_revision":"2020-10-26","fecha_compra":"2020-01-08","matricula":"6756-DSX","documentacion":"prueba.txt"},{"fecha_revision":"2021-01-16","fecha_compra":"2020-04-03","matricula":"8967-BLC","documentacion":"prueba.txt"},{"fecha_revision":"2020-10-23","fecha_compra":"2020-04-14","matricula":"7824-BBB","documentacion":"prueba.txt"},{"fecha_revision":"2022-04-14","fecha_compra":"2020-01-14","matricula":"9545-KKK","documentacion":"prueba.txt"},{"fecha_revision":"2020-04-30","fecha_compra":"2020-04-06","matricula":"7548-GGG","documentacion":"prueba.txt"},{"fecha_revision":"2021-01-08","fecha_compra":"2019-10-08","matricula":"3823-DJK","documentacion":"Protocolo.pdf"}]}